potatoutils/__init__.py
potatoutils/util.py
potatoutils/abstractions/Comparable.py
potatoutils/abstractions/__init__.py
tests/__init__.py
tests/test_util.py
potatoutils-0.0.3.dist-info/METADATA
potatoutils-0.0.3.dist-info/WHEEL
potatoutils-0.0.3.dist-info/top_level.txt
potatoutils-0.0.3.dist-info/RECORD
