Metadata-Version: 2.1
Name: potatoutils
Version: 0.0.3
Summary: My first Python library
Home-page: UNKNOWN
Author: Dorijan Cirkveni
Author-email: UNKNOWN
License: MIT
Platform: UNKNOWN
